syft_nsai/__init__.py
syft_nsai/py.typed
syft_nsai-0.1.1.dist-info/METADATA
syft_nsai-0.1.1.dist-info/WHEEL
syft_nsai-0.1.1.dist-info/licenses/LICENSE
syft_nsai-0.1.1.dist-info/RECORD
