Metadata-Version: 2.4
Name: syft-nsai
Version: 0.1.1
Summary: OpenAI-compatible interface for using SyftBox datasets with AI models in secure enclaves
Project-URL: Homepage, https://github.com/OpenMined/syft-nsai
Project-URL: Documentation, https://github.com/OpenMined/syft-nsai#readme
Project-URL: Repository, https://github.com/OpenMined/syft-nsai
Project-URL: Issues, https://github.com/OpenMined/syft-nsai/issues
Project-URL: Changelog, https://github.com/OpenMined/syft-nsai/releases
Author-email: OpenMined <info@openmined.org>
License-Expression: Apache-2.0
License-File: LICENSE
Keywords: ai,datasets,enclaves,federated-learning,openai,privacy,syft
Classifier: Development Status :: 4 - Beta
Classifier: Intended Audience :: Developers
Classifier: License :: OSI Approved :: Apache Software License
Classifier: Operating System :: OS Independent
Classifier: Programming Language :: Python :: 3
Classifier: Programming Language :: Python :: 3.12
Classifier: Topic :: Scientific/Engineering :: Artificial Intelligence
Classifier: Topic :: Security :: Cryptography
Classifier: Topic :: Software Development :: Libraries :: Python Modules
Requires-Python: >=3.12
Requires-Dist: syft-core
Requires-Dist: syft-datasets>=0.2.0
Requires-Dist: syft-rds
Requires-Dist: syft-wallet>=0.1.1
Requires-Dist: syftbox-enclave
Requires-Dist: typing-extensions>=4.0.0
Provides-Extra: dev
Requires-Dist: coverage[toml]>=7.0.0; extra == 'dev'
Requires-Dist: mypy>=1.7.0; extra == 'dev'
Requires-Dist: pre-commit>=3.0.0; extra == 'dev'
Requires-Dist: pytest-asyncio>=0.21.0; extra == 'dev'
Requires-Dist: pytest-mock>=3.10.0; extra == 'dev'
Requires-Dist: pytest>=7.0.0; extra == 'dev'
Requires-Dist: ruff>=0.1.0; extra == 'dev'
Requires-Dist: types-requests; extra == 'dev'
